statuscheck/__about__.py
statuscheck/__init__.py
statuscheck/cli.py
statuscheck/utils.py
statuscheck/services/__init__.py
statuscheck/services/airtable.py
statuscheck/services/asana.py
statuscheck/services/atlassian.py
statuscheck/services/basecamp.py
statuscheck/services/bitbucket.py
statuscheck/services/circleci.py
statuscheck/services/close.py
statuscheck/services/cloudamqp.py
statuscheck/services/cloudflare.py
statuscheck/services/clubhouse.py
statuscheck/services/codecov.py
statuscheck/services/confluence.py
statuscheck/services/coveralls.py
statuscheck/services/digitalocean.py
statuscheck/services/discord.py
statuscheck/services/dnsimple.py
statuscheck/services/docker.py
statuscheck/services/epicgames.py
statuscheck/services/fastly.py
statuscheck/services/gandi.py
statuscheck/services/geckoboard.py
statuscheck/services/github.py
statuscheck/services/gitlab.py
statuscheck/services/heroku.py
statuscheck/services/invision.py
statuscheck/services/jira.py
statuscheck/services/mailgun.py
statuscheck/services/newrelic.py
statuscheck/services/npm.py
statuscheck/services/nylas.py
statuscheck/services/ownbackup.py
statuscheck/services/pagerduty.py
statuscheck/services/personio.py
statuscheck/services/pypi.py
statuscheck/services/redislabs.py
statuscheck/services/salesforce.py
statuscheck/services/sendgrid.py
statuscheck/services/sentry.py
statuscheck/services/servicemax.py
statuscheck/services/signal.py
statuscheck/services/slack.py
statuscheck/services/sparkpost.py
statuscheck/services/travis.py
statuscheck/services/trello.py
statuscheck/services/twilio.py
statuscheck/services/twitter.py
statuscheck/services/vercel.py
statuscheck/services/zoom.py
statuscheck/services/bases/__init__.py
statuscheck/services/bases/_base.py
statuscheck/services/bases/_statusio.py
statuscheck/services/bases/_statuspageio.py
statuscheck/services/models/__init__.py
statuscheck/services/models/generic.py
statuscheck-3.11.0.dist-info/LICENSE
statuscheck-3.11.0.dist-info/METADATA
statuscheck-3.11.0.dist-info/WHEEL
statuscheck-3.11.0.dist-info/entry_points.txt
statuscheck-3.11.0.dist-info/top_level.txt
statuscheck-3.11.0.dist-info/RECORD
