Metadata-Version: 2.1
Name: statuscheck
Version: 3.11.0
Summary: Tool to check PaaS/SaaS status pages
Home-page: https://github.com/amureki/statuscheck
Author: Rust Saiargaliev
Author-email: amureki@hey.com
License: Apache Software License 2.0
Keywords: statuscheck
Platform: UNKNOWN
Classifier: Development Status :: 4 - Beta
Classifier: Intended Audience :: Developers
Classifier: License :: OSI Approved :: Apache Software License
Classifier: Natural Language :: English
Classifier: Programming Language :: Python :: 3
Classifier: Programming Language :: Python :: 3.6
Classifier: Programming Language :: Python :: 3.7
Classifier: Programming Language :: Python :: 3.8
Classifier: Programming Language :: Python :: 3.9
Requires-Dist: Click (==7.1.2)
Requires-Dist: httpx (==0.16.1)
Requires-Dist: attrs (==20.3.0)
Provides-Extra: tests
Requires-Dist: coverage ; extra == 'tests'
Requires-Dist: pytest ; extra == 'tests'
Requires-Dist: respx ; extra == 'tests'
